prf/__init__.py
prf/auth.py
prf/csv.py
prf/es.py
prf/exc.py
prf/mongodb.py
prf/renderers.py
prf/request.py
prf/resource.py
prf/s3.py
prf/sentry.py
prf/serializer.py
prf/sqla.py
prf/sqlite.py
prf/tweens.py
prf/utility_views.py
prf/view.py
prf/scripts/__init__.py
prf/scripts/common.py
prf/scripts/control.py
prf/scripts/init_db.py
prf/scripts/mongo_index.py
prf/tests/__init__.py
prf/tests/prf_testcase.py
prf/tests/test_csv.py
prf/tests/test_exc.py
prf/tests/test_mongodb.py
prf/tests/test_prf.py
prf/tests/test_request.py
prf/tests/test_resource.py
prf/tests/test_utils.py
prf/tests/test_view.py
prf/utils/__init__.py
prf/utils/csv.py
prf/utils/errors.py
prf/utils/utils.py
prf-1.0.2.dist-info/LICENSE
prf-1.0.2.dist-info/METADATA
prf-1.0.2.dist-info/WHEEL
prf-1.0.2.dist-info/entry_points.txt
prf-1.0.2.dist-info/top_level.txt
prf-1.0.2.dist-info/RECORD
