Metadata-Version: 2.1
Name: prf
Version: 1.0.2
Summary: PRF is designed to help coding RESTful endpoints with minimal code
Home-page: UNKNOWN
Author: vahan
Author-email: aivosha@gmail.com
License: UNKNOWN
Keywords: web wsgi bfg pylons pyramid rest
Platform: UNKNOWN
Classifier: Programming Language :: Python
Classifier: Framework :: Pyramid
Classifier: Topic :: Internet :: WWW/HTTP
Classifier: Topic :: Internet :: WWW/HTTP :: WSGI :: Application
Requires-Dist: pyramid
Requires-Dist: slovar
Requires-Dist: requests
Requires-Dist: mongoengine
